setup.py
libsovereign/__init__.py
libsovereign.egg-info/PKG-INFO
libsovereign.egg-info/SOURCES.txt
libsovereign.egg-info/dependency_links.txt
libsovereign.egg-info/top_level.txt
libsovereign/const/__init__.py
libsovereign/const/crm.py