Metadata-Version: 1.1
Name: libsovereign
Version: 1.0.0alpha1
Summary: A Python shared library for the Sovereign system.
Home-page: https://www.sousouindustries.com/
Author: Cochise Ruhulessin
Author-email: cochise.ruhulessin@sousouindustries.com
License: Apache Licence 2.0
Platform: UNKNOWN
Classifier: Development Status :: 2 - Pre-Alpha
Classifier: Environment :: Web Environment
Classifier: Programming Language :: Python
Classifier: Programming Language :: Python :: 2
Classifier: Programming Language :: Python :: 2.7
Classifier: Programming Language :: Python :: 3
Classifier: Programming Language :: Python :: 3.4
Classifier: Programming Language :: Python :: 3.5
Classifier: Topic :: Software Development :: Libraries :: Python Modules
